psi/__init__.py
psi/_version.py
psi/util.py
psi/version.py
psi/application/__init__.py
psi/application/api.py
psi/application/psi_launcher.py
psi/context/__init__.py
psi/context/api.py
psi/context/choice.py
psi/context/context_item.py
psi/context/context_item_manifest.enaml
psi/context/context_item_view.enaml
psi/context/expression.py
psi/context/manifest.enaml
psi/context/plugin.py
psi/context/selector.py
psi/context/selector_manifest.enaml
psi/context/symbol.py
psi/controller/__init__.py
psi/controller/api.py
psi/controller/channel.py
psi/controller/channel_manifest.enaml
psi/controller/engine.py
psi/controller/engine_manifest.enaml
psi/controller/experiment_action.py
psi/controller/input.py
psi/controller/input_manifest.enaml
psi/controller/input_primitives.enaml
psi/controller/manifest.enaml
psi/controller/output.py
psi/controller/output_manifest.enaml
psi/controller/plugin.py
psi/controller/util.py
psi/controller/calibration/__init__.py
psi/controller/calibration/acquire.py
psi/controller/calibration/api.py
psi/controller/calibration/calibrate.py
psi/controller/calibration/calibrate_manifest.enaml
psi/controller/calibration/chirp.py
psi/controller/calibration/click.py
psi/controller/calibration/manifest.enaml
psi/controller/calibration/plugin.py
psi/controller/calibration/tone.py
psi/controller/calibration/util.py
psi/controller/engines/__init__.py
psi/controller/engines/nidaq.py
psi/controller/engines/null.py
psi/controller/engines/biosemi/__init__.py
psi/controller/engines/biosemi/channel_maps.py
psi/controller/engines/biosemi/electrode_coords.py
psi/controller/engines/biosemi/electrode_coords_32.csv
psi/controller/engines/biosemi/electrode_coords_64.csv
psi/controller/engines/biosemi/electrode_selector.py
psi/controller/engines/biosemi/electrode_selector_view.enaml
psi/controller/engines/biosemi/exg_coords.csv
psi/controller/engines/biosemi/inputs.py
psi/controller/engines/biosemi/mapped_electrode_coords_32_exg.csv
psiexperiment-0.6.3.dist-info/LICENSE.txt
psiexperiment-0.6.3.dist-info/METADATA
psiexperiment-0.6.3.dist-info/WHEEL
psiexperiment-0.6.3.dist-info/entry_points.txt
psiexperiment-0.6.3.dist-info/top_level.txt
psiexperiment-0.6.3.dist-info/RECORD
