Metadata-Version: 2.2
Name: psiexperiment
Version: 0.6.3
Summary: Framework for running trial-based experiments
Author-email: Brad Buran <bburan@alum.mit.edu>, Brad Buran <buran@ohsu.edu>, "Buran Consulting, LLC" <info@bradburan.com>
Maintainer-email: Brad Buran <bburan@alum.mit.edu>, Brad Buran <buran@ohsu.edu>, "Buran Consulting, LLC" <info@bradburan.com>
License: MIT License
Requires-Python: >=3.7
License-File: LICENSE.txt
Requires-Dist: psidata>=0.1.7
Requires-Dist: psiaudio>=0.2.4
Requires-Dist: enaml>=0.13.0
Requires-Dist: numpy
Requires-Dist: palettable
Requires-Dist: pyqtgraph>=0.11.0
Requires-Dist: scipy
Requires-Dist: pandas
Requires-Dist: pyyaml
Requires-Dist: pywin32; os_name == "nt"
Requires-Dist: websockets
Provides-Extra: ni
Requires-Dist: pydaqmx; extra == "ni"
Provides-Extra: tdt
Requires-Dist: tdtpy>=0.10.2; extra == "tdt"
Provides-Extra: docs
Requires-Dist: sphinx; extra == "docs"
Requires-Dist: sphinx_rtd_theme; extra == "docs"
Requires-Dist: pygments-enaml; extra == "docs"
Provides-Extra: test
Requires-Dist: pytest; extra == "test"
Requires-Dist: pytest-console-scripts; extra == "test"
Requires-Dist: matplotlib; extra == "test"
Provides-Extra: zarr
Requires-Dist: zarr; extra == "zarr"
Provides-Extra: dev
Requires-Dist: coloredlogs; extra == "dev"
